[
  {
    "日期Date": 20260622,
    "股息率1（总股本）D/P1": 5.09,
    "股息率2（计算用股本）D/P2": 5.23
  },
  {
    "日期Date": 20260623,
    "股息率1（总股本）D/P1": 5.04,
    "股息率2（计算用股本）D/P2": 5.23
  },
  {
    "日期Date": 20260624,
    "股息率1（总股本）D/P1": 5.16,
    "股息率2（计算用股本）D/P2": 5.34
  },
  {
    "日期Date": 20260625,
    "股息率1（总股本）D/P1": 5.2,
    "股息率2（计算用股本）D/P2": 5.39
  },
  {
    "日期Date": 20260626,
    "股息率1（总股本）D/P1": 5.26,
    "股息率2（计算用股本）D/P2": 5.46
  },
  {
    "日期Date": 20260629,
    "股息率1（总股本）D/P1": 5.21,
    "股息率2（计算用股本）D/P2": 5.39
  },
  {
    "日期Date": 20260630,
    "股息率1（总股本）D/P1": 5.24,
    "股息率2（计算用股本）D/P2": 5.05
  },
  {
    "日期Date": 20260701,
    "股息率1（总股本）D/P1": 5.21,
    "股息率2（计算用股本）D/P2": 4.97
  },
  {
    "日期Date": 20260702,
    "股息率1（总股本）D/P1": 5.19,
    "股息率2（计算用股本）D/P2": 4.92
  },
  {
    "日期Date": 20260703,
    "股息率1（总股本）D/P1": 5.19,
    "股息率2（计算用股本）D/P2": 4.89
  },
  {
    "日期Date": 20260706,
    "股息率1（总股本）D/P1": 5.12,
    "股息率2（计算用股本）D/P2": 4.82
  },
  {
    "日期Date": 20260707,
    "股息率1（总股本）D/P1": 5.12,
    "股息率2（计算用股本）D/P2": 4.88
  },
  {
    "日期Date": 20260708,
    "股息率1（总股本）D/P1": 5.06,
    "股息率2（计算用股本）D/P2": 4.84
  },
  {
    "日期Date": 20260709,
    "股息率1（总股本）D/P1": 5.1,
    "股息率2（计算用股本）D/P2": 4.89
  },
  {
    "日期Date": 20260710,
    "股息率1（总股本）D/P1": 5.08,
    "股息率2（计算用股本）D/P2": 4.88
  },
  {
    "日期Date": 20260713,
    "股息率1（总股本）D/P1": 5.01,
    "股息率2（计算用股本）D/P2": 4.83
  },
  {
    "日期Date": 20260714,
    "股息率1（总股本）D/P1": 4.99,
    "股息率2（计算用股本）D/P2": 4.79
  },
  {
    "日期Date": 20260715,
    "股息率1（总股本）D/P1": 4.94,
    "股息率2（计算用股本）D/P2": 4.72
  },
  {
    "日期Date": 20260716,
    "股息率1（总股本）D/P1": 4.98,
    "股息率2（计算用股本）D/P2": 4.73
  },
  {
    "日期Date": 20260717,
    "股息率1（总股本）D/P1": 4.94,
    "股息率2（计算用股本）D/P2": 4.74
  }
]